seaplane/cli/__init__.py
seaplane/cli/__main__.py
seaplane/cli/auth.py
seaplane/cli/command.py
seaplane/cli/endpoints.py
seaplane/cli/flows.py
seaplane/cli/kv.py
seaplane/cli/objects.py
seaplane/cli/streams.py
seaplane/cli/util.py
seaplane.cli-0.0.20.dist-info/LICENSE
seaplane.cli-0.0.20.dist-info/METADATA
seaplane.cli-0.0.20.dist-info/WHEEL
seaplane.cli-0.0.20.dist-info/entry_points.txt
seaplane.cli-0.0.20.dist-info/top_level.txt
seaplane.cli-0.0.20.dist-info/RECORD
