Metadata-Version: 2.1
Name: seaplane.cli
Version: 0.0.20
Home-page: 
Author: Seaplane IO, Inc.
Author-email: support@seaplane.io
License: Apache 2.0
Keywords: Seaplane,CLI
Requires-Python: >=3.7
License-File: LICENSE
Requires-Dist: PyJWT ==2.8.0
Requires-Dist: PyYAML ==6.0.1
Requires-Dist: click ==8.1.3
Requires-Dist: seaplane.api ==0.0.15
Requires-Dist: seaplane.common ==0.0.2
Requires-Dist: seaplane.config ==0.0.5
Requires-Dist: tabulate
Requires-Dist: urllib3 >=1.25.3
